agentci/client_config/__init__.py
agentci/client_config/_config.py
agentci/client_config/evals/__init__.py
agentci/client_config/evals/parser.py
agentci/client_config/evals/schema.py
agentci/client_config/frameworks/__init__.py
agentci/client_config/frameworks/parser.py
agentci/client_config/frameworks/schema.py
agentci/client_config/frameworks/configs/langchain.toml
agentci/client_config/frameworks/configs/llamaindex.toml
agentci/client_config/frameworks/configs/openai_agents.toml
agentci/client_config/frameworks/configs/pydantic_ai.toml
agentci_client_config-0.1.2.dist-info/METADATA
agentci_client_config-0.1.2.dist-info/WHEEL
agentci_client_config-0.1.2.dist-info/licenses/LICENSE
agentci_client_config-0.1.2.dist-info/RECORD
