Metadata-Version: 2.4
Name: agentci-client-config
Version: 0.1.2
Summary: Client configuration for AgentCI
Author-email: Agent CI <hello@agent-ci.com>, Travis Dent <root@a10k.co>
License-File: LICENSE
Requires-Python: >=3.11
Requires-Dist: pydantic-settings>=2.0.0
Requires-Dist: pydantic>=2.0.0
Provides-Extra: docs
Requires-Dist: mkdocs-material>=9.0.0; extra == 'docs'
Requires-Dist: mkdocs>=1.5.0; extra == 'docs'
Requires-Dist: mkdocstrings[python]>=0.24.0; extra == 'docs'
Provides-Extra: test
Requires-Dist: pytest-cov>=4.0.0; extra == 'test'
Requires-Dist: pytest>=7.0.0; extra == 'test'
